json_differ/__init__.py
json_differ/cli.py
json_differ/core.py
json_differ-1.0.0.dist-info/licenses/LICENSE
json_differ-1.0.0.dist-info/METADATA
json_differ-1.0.0.dist-info/WHEEL
json_differ-1.0.0.dist-info/entry_points.txt
json_differ-1.0.0.dist-info/top_level.txt
json_differ-1.0.0.dist-info/RECORD
