Metadata-Version: 2.4
Name: json-differ
Version: 1.0.0
Summary: A minimal, human-readable JSON difference tool.
Author-email: Syed Rakesh Uddin <syedrakeshuddin@gmail.com>
License: MIT
Keywords: json,diff,compare,cli,developer-tool
Requires-Python: >=3.7
License-File: LICENSE
Dynamic: license-file
